[
  {
    "name": "Skergling",
    "lobby": null,
    "lastSeen": 1740125489907,
    "prestige": "XXI",
    "level": 107
  },
  {
    "name": "AsterLight ♚",
    "lobby": "mega1G",
    "lastSeen": 1740126528534,
    "prestige": "XXXIV",
    "level": 84
  },
  {
    "name": "RealJu4n ♚",
    "lobby": "mega1A",
    "lastSeen": 1740107034505,
    "prestige": "IX",
    "level": 72
  },
  {
    "name": "funkybanana28",
    "lobby": "mega1A",
    "lastSeen": 1740102073664,
    "prestige": "XX",
    "level": 59
  },
  {
    "name": "ItsEmmanGaming",
    "lobby": null,
    "lastSeen": 1740109032515,
    "prestige": "XXXVI",
    "level": 100
  },
  {
    "name": "4usb",
    "lobby": "mega1G",
    "lastSeen": 1740132473721,
    "prestige": "XXXI",
    "level": 117,
    "guild": "MIST"
  },
  {
    "name": "Wadmol",
    "lobby": "mega1D",
    "lastSeen": 1740132637115
  },
  {
    "name": "lonewy",
    "lobby": "mega1G",
    "lastSeen": 1740132607123
  },
  {
    "name": "lovedey",
    "lobby": null,
    "lastSeen": 1740101985665,
    "prestige": "LVI",
    "level": 120,
    "guild": "MOON",
    "rank": "MVP+"
  },
  {
    "name": "kiqx",
    "lobby": "mega1G",
    "lastSeen": 1740101863661,
    "prestige": "XLVI",
    "level": 77,
    "guild": "BOO",
    "rank": "MVP+"
  },
  {
    "name": "Dragonrider7813",
    "lobby": null,
    "lastSeen": 1740101639085
  },
  {
    "name": "ywous",
    "lobby": "mega1H",
    "lastSeen": 1740109554409,
    "prestige": "LX",
    "level": 109,
    "guild": "ENVY",
    "rank": "MVP"
  },
  {
    "name": "Silvercottonn",
    "lobby": "mega1A",
    "lastSeen": 1740103847965
  },
  {
    "name": "TimingCookie586 ♚",
    "lobby": "mega1A",
    "lastSeen": 1740101082268,
    "prestige": "XXI",
    "level": 109,
    "guild": "MIST"
  },
  {
    "name": "holidaysz",
    "lobby": null,
    "lastSeen": 1740126668800,
    "prestige": "XVI",
    "level": 120
  },
  {
    "name": "0WAVE",
    "prestige": "XIII",
    "level": 73,
    "lastSeen": 1740100923724,
    "lobby": "mega1F"
  },
  {
    "name": "JuanTwoThreee",
    "lobby": "mega1C",
    "lastSeen": 1740100849547
  },
  {
    "name": "Weeklydeer ♚",
    "lobby": "mega1H",
    "lastSeen": 1740118310782,
    "prestige": "LXV",
    "level": 106,
    "guild": "MOON",
    "rank": "MVP+"
  },
  {
    "name": "kezirish",
    "lobby": "mega1E",
    "lastSeen": 1740127633500,
    "prestige": "LX",
    "level": 104,
    "guild": "MVP"
  },
  {
    "name": "WhyYouSoSlow",
    "lobby": "mega1F",
    "lastSeen": 1740103367893,
    "prestige": "XV",
    "level": 120
  },
  {
    "name": "Nubxiee",
    "lobby": "mega1C",
    "lastSeen": 1740100849545
  },
  {
    "name": "knify0_1",
    "lobby": "mega1F",
    "lastSeen": 1740103387834,
    "prestige": "XXVIII",
    "level": 100
  },
  {
    "name": "superbent",
    "lobby": "mega1H",
    "lastSeen": 1740100570295,
    "prestige": "LII",
    "level": 116,
    "guild": "ENVY",
    "rank": "MVP+"
  },
  {
    "name": "ProIronHumbler ♚",
    "lobby": "mega1H",
    "lastSeen": 1740118305897,
    "prestige": "LVI",
    "level": 115,
    "guild": "MOON",
    "rank": "MVP+"
  },
  {
    "name": "Badboy_22",
    "lobby": null,
    "lastSeen": 1740119587111
  },
  {
    "name": "SillyMunkey ♚",
    "lobby": "mega1H",
    "lastSeen": 1740118308704,
    "prestige": "LVII",
    "level": 110,
    "guild": "MOON",
    "rank": "MVP"
  },
  {
    "name": "Donderweer",
    "lobby": "mega1G",
    "lastSeen": 1740129763941,
    "prestige": "XLVIII",
    "level": 77,
    "guild": "MOON",
    "rank": "VIP"
  },
  {
    "name": "daisyylover",
    "lobby": "mega1G",
    "lastSeen": 1740106183150
  },
  {
    "name": "himynameishejjo",
    "lobby": "mega1H",
    "lastSeen": 1740100545737,
    "prestige": "LVI",
    "level": 118,
    "guild": "BOO",
    "rank": "MVP"
  },
  {
    "name": "RageQuitForMePls",
    "lobby": "mega1A",
    "lastSeen": 1740100365841,
    "prestige": "XXXIII",
    "level": 120
  },
  {
    "name": "RuRuRemen",
    "lobby": null,
    "lastSeen": 1740127868344,
    "prestige": "LIV",
    "level": 80,
    "guild": "VIP"
  },
  {
    "name": "vnL00L",
    "prestige": "LXX",
    "level": 120,
    "guild": "MOON",
    "rank": "MVP",
    "lastSeen": 1740118305195,
    "lobby": "mega1H"
  },
  {
    "name": "NeverGlitch",
    "lobby": "mega1H",
    "lastSeen": 1740100244742,
    "prestige": "XLVI",
    "level": 57,
    "guild": "MVP"
  },
  {
    "name": "In_Low_Ping",
    "lobby": null,
    "lastSeen": 1740099985773,
    "prestige": "X",
    "level": 115
  },
  {
    "name": "40UP",
    "lobby": "mega1A",
    "lastSeen": 1740110004561
  },
  {
    "name": "Trilxxx",
    "lobby": null,
    "lastSeen": 1740099940304
  },
  {
    "name": "AppleFromTree",
    "lobby": null,
    "lastSeen": 1740099919393
  },
  {
    "name": "Teakwood13",
    "lobby": null,
    "lastSeen": 1740104900832
  },
  {
    "name": "Jerzide",
    "lobby": null,
    "lastSeen": 1740099134387
  },
  {
    "name": "WinBlue",
    "lobby": "mega1A",
    "lastSeen": 1740099096332
  },
  {
    "name": "AespaKarinaJPTop",
    "lobby": "mega1E",
    "lastSeen": 1740125465214
  },
  {
    "name": "yBlackG0D",
    "lobby": "mega1A",
    "lastSeen": 1740098976346,
    "prestige": "XI",
    "level": 120
  },
  {
    "name": "Thoused",
    "lobby": null,
    "lastSeen": 1740098941196
  },
  {
    "name": "RightHippo",
    "lobby": "mega1F",
    "lastSeen": 1740098737038
  },
  {
    "name": "sissy",
    "lobby": "mega1H",
    "lastSeen": 1740098697719,
    "prestige": "LXIX",
    "level": 107,
    "guild": "WRLD",
    "rank": "MVP+"
  },
  {
    "name": "TryMeDaughter",
    "lobby": "mega1H",
    "lastSeen": 1740109554410,
    "prestige": "XLIX",
    "level": 112,
    "guild": "E",
    "rank": "MVP"
  },
  {
    "name": "How2BSigma",
    "lobby": "mega1H",
    "lastSeen": 1740098676142
  },
  {
    "name": "ThePogChampers",
    "lobby": null,
    "lastSeen": 1740098599103
  },
  {
    "name": "Mystic500k",
    "lobby": "mega1F",
    "lastSeen": 1740098261879,
    "prestige": "XLV",
    "level": 114,
    "guild": "DETH"
  },
  {
    "name": "sprays",
    "lobby": "mega1F",
    "lastSeen": 1740098069875
  },
  {
    "name": "jx6",
    "lobby": "mega1F",
    "lastSeen": 1740098025596
  },
  {
    "name": "Ourato",
    "lobby": null,
    "lastSeen": 1740097846631
  },
  {
    "name": "LenLep",
    "lobby": null,
    "lastSeen": 1740097549972
  },
  {
    "name": "Ermatiel",
    "lobby": "mega1C",
    "lastSeen": 1740097536789
  },
  {
    "name": "rosebvnny",
    "lobby": null,
    "lastSeen": 1740097353160,
    "prestige": "XL",
    "level": 72,
    "guild": "Fish"
  },
  {
    "name": "stimp7986",
    "lobby": null,
    "lastSeen": 1740127701297,
    "prestige": "VI",
    "level": 102
  },
  {
    "name": "nucleur",
    "lobby": "mega1A",
    "lastSeen": 1740109344315,
    "prestige": "XLII",
    "level": 113,
    "guild": "MOON",
    "rank": "MVP"
  },
  {
    "name": "avaean",
    "lobby": null,
    "lastSeen": 1740107158936,
    "prestige": "XVIII",
    "level": 112
  },
  {
    "name": "madelynluvsu",
    "lobby": null,
    "lastSeen": 1740103361235
  },
  {
    "name": "zBagq",
    "lobby": "mega1A",
    "lastSeen": 1740103720967
  },
  {
    "name": "2hours_clean",
    "lobby": null,
    "lastSeen": 1740104353655
  },
  {
    "name": "2x4l",
    "lobby": null,
    "lastSeen": 1740118549626
  },
  {
    "name": "Niters",
    "lobby": "mega1F",
    "lastSeen": 1740107510176,
    "prestige": "XLIII",
    "level": 98,
    "guild": "VIP"
  },
  {
    "name": "vrae",
    "lobby": "mega1G",
    "lastSeen": 1740105256012
  },
  {
    "name": "Qwintesla",
    "lobby": "mega1G",
    "lastSeen": 1740110034456,
    "prestige": "XXIX",
    "level": 92
  },
  {
    "name": "iLizzyIsCute",
    "lobby": "mega1C",
    "lastSeen": 1740122511333,
    "prestige": "LX",
    "level": 120,
    "guild": "MOON",
    "rank": "MVP+"
  },
  {
    "name": "xymv",
    "lobby": "mega1G",
    "lastSeen": 1740106303258,
    "prestige": "XXX",
    "level": 120,
    "guild": "FEAR"
  },
  {
    "name": "Goatat0chip",
    "lobby": null,
    "lastSeen": 1740106511657
  },
  {
    "name": "HeBeBig",
    "lobby": null,
    "lastSeen": 1740106865360
  },
  {
    "name": "NateStone",
    "lobby": "mega1A",
    "lastSeen": 1740109216634,
    "prestige": "XIII",
    "level": 81
  },
  {
    "name": "robiseqqqq",
    "lobby": null,
    "lastSeen": 1740107705940
  },
  {
    "name": "LegitSmurf",
    "lobby": "mega1A",
    "lastSeen": 1740108238179,
    "prestige": "XXXIII",
    "level": 61
  },
  {
    "name": "Sorky",
    "lobby": "mega1A",
    "lastSeen": 1740108238180,
    "prestige": "XXXVII",
    "level": 61,
    "guild": "FEAR",
    "rank": "VIP"
  },
  {
    "name": "Zzennvs",
    "lobby": "mega1A",
    "lastSeen": 1740107660586
  },
  {
    "name": "TTrain_Cooper",
    "lobby": "mega1C",
    "lastSeen": 1740119602467,
    "prestige": "XLIII",
    "level": 100,
    "guild": "MIST",
    "rank": "MVP+"
  },
  {
    "name": "iBackStrap",
    "lobby": null,
    "lastSeen": 1740109032520
  },
  {
    "name": "United_Mewing",
    "lobby": null,
    "lastSeen": 1740109312893
  },
  {
    "name": "dahssnn",
    "lobby": null,
    "lastSeen": 1740109189949
  },
  {
    "name": "Nextpls",
    "lobby": "mega1E",
    "lastSeen": 1740128773656
  },
  {
    "name": "CocoLovesDinos",
    "lobby": null,
    "lastSeen": 1740119222442
  },
  {
    "name": "longabuser",
    "lobby": "mega1G",
    "lastSeen": 1740118679356
  },
  {
    "name": "HERMIT4CHINA",
    "lobby": "mega1E",
    "lastSeen": 1740129013914
  },
  {
    "name": "WNOW",
    "lobby": null,
    "lastSeen": 1740121976782,
    "prestige": "XXI",
    "level": 112
  },
  {
    "name": "GTFS",
    "lobby": null,
    "lastSeen": 1740122971142,
    "prestige": "XLVIII",
    "level": 78,
    "guild": "BOO",
    "rank": "MVP+"
  },
  {
    "name": "DataDash2D",
    "lobby": "mega1D",
    "lastSeen": 1740129853842,
    "prestige": "XVI",
    "level": 109
  },
  {
    "name": "yoyowkyi",
    "lobby": null,
    "lastSeen": 1740121602021
  },
  {
    "name": "nomufz",
    "lobby": null,
    "lastSeen": 1740121829833
  },
  {
    "name": "FelenaArdoni",
    "lobby": null,
    "lastSeen": 1740121799858
  },
  {
    "name": "JackFlame",
    "lobby": "mega1C",
    "lastSeen": 1740122923329,
    "prestige": "XLV",
    "level": 120,
    "guild": "BOO",
    "rank": "MVP"
  },
  {
    "name": "LaParilla",
    "lobby": null,
    "lastSeen": 1740123265891,
    "prestige": "XLV",
    "level": 110,
    "guild": "Ham",
    "rank": "MVP"
  },
  {
    "name": "tacz",
    "lobby": "mega1D",
    "lastSeen": 1740128293690,
    "prestige": "LXV",
    "level": 119,
    "guild": "ENVY",
    "rank": "MVP"
  },
  {
    "name": "lemonwow1",
    "lobby": "mega1D",
    "lastSeen": 1740122745728
  },
  {
    "name": "Skepno",
    "lobby": "mega1D",
    "lastSeen": 1740132637116,
    "prestige": "XXIV",
    "level": 56,
    "guild": "VIP"
  },
  {
    "name": "ICfMirrorOMG",
    "lobby": "mega1C",
    "lastSeen": 1740125555207
  },
  {
    "name": "Mealoan",
    "lobby": "mega1G",
    "lastSeen": 1740132607122
  },
  {
    "name": "ChillUser",
    "lobby": "mega1G",
    "lastSeen": 1740127543510
  },
  {
    "name": "catboyharry",
    "lobby": null,
    "lastSeen": 1740126561108
  },
  {
    "name": "vexbladeCZ",
    "lobby": "mega1D",
    "lastSeen": 1740128293691,
    "prestige": "XXIV",
    "level": 94
  },
  {
    "name": "Cybertrash_",
    "lobby": "mega1G",
    "lastSeen": 1740132607123,
    "prestige": "XXIX",
    "level": 79
  },
  {
    "name": "Kolijn",
    "lobby": "mega1E",
    "lastSeen": 1740127633500
  },
  {
    "name": "lunovox_",
    "lobby": "mega1G",
    "lastSeen": 1740132607121
  },
  {
    "name": "Spiritua1",
    "lobby": null,
    "lastSeen": 1740132540221
  },
  {
    "name": "RoundOver",
    "lobby": "mega1G",
    "lastSeen": 1740129703930,
    "prestige": "XXXIII",
    "level": 76
  },
  {
    "name": "QuiteNoob",
    "lobby": "mega1G",
    "lastSeen": 1740130855981,
    "prestige": "XXXII",
    "level": 34,
    "guild": "MIST"
  },
  {
    "name": "revived_37h__",
    "lobby": "mega1E",
    "lastSeen": 1740129013914
  },
  {
    "name": "maotsms",
    "lobby": "mega1E",
    "lastSeen": 1740129013914,
    "prestige": "XV",
    "level": 116
  },
  {
    "name": "NPCCrusher",
    "lobby": null,
    "lastSeen": 1740131410334
  },
  {
    "name": "ImSpy",
    "lobby": null,
    "lastSeen": 1740128994439
  },
  {
    "name": "g550",
    "lobby": "mega1C",
    "lastSeen": 1740129584086
  },
  {
    "name": "30193",
    "lobby": null,
    "lastSeen": 1740129931058
  },
  {
    "name": "baba_owo",
    "lobby": null,
    "lastSeen": 1740131478835,
    "prestige": "XLIII",
    "level": 76
  },
  {
    "name": "Folour_games",
    "lobby": null,
    "lastSeen": 1740131730016
  },
  {
    "name": "TTTTo4578",
    "lobby": "mega1G",
    "lastSeen": 1740131399212,
    "prestige": "XXXVIII",
    "level": 63,
    "guild": "TNO",
    "rank": "MVP"
  },
  {
    "name": "MC_Einar",
    "lobby": null,
    "lastSeen": 1740131626510
  },
  {
    "name": "ILoveWhiteicecat",
    "lobby": "mega1D",
    "lastSeen": 1740132383771
  },
  {
    "name": "Buyo77",
    "lobby": "mega1G",
    "lastSeen": 1740132607121,
    "prestige": "XLVI",
    "level": 111,
    "guild": "LaLa",
    "rank": "VIP"
  },
  {
    "name": "krostygg",
    "lobby": "mega1G",
    "lastSeen": 1740132607122
  }
]